dischub_bot/__init__.py
dischub_bot/bot_logic.py
dischub_bot/client.py
dischub_bot/context_processors.py
dischub_bot/db.py
dischub_bot/exceptions.py
dischub_bot/main.py
dischub_bot/models.py
dischub_bot/settings.py
dischub_bot/urls.py
dischub_bot/views.py
dischub_bot/migrations/0001_initial.py
dischub_bot/migrations/0002_symbolsettings.py
dischub_bot/migrations/0003_alter_symbolsettings_created_at.py
dischub_bot/migrations/0004_alter_paymentverification_verified_at_and_more.py
dischub_bot/migrations/0005_remove_paymentverification_verified_at_and_more.py
dischub_bot/migrations/0006_mt5account.py
dischub_bot/migrations/0007_delete_mt5account.py
dischub_bot/migrations/0008_alter_paymentverification_id_alter_symbolsettings_id.py
dischub_bot/migrations/0009_alter_paymentverification_id_alter_symbolsettings_id.py
dischub_bot/migrations/__init__.py
dischub_bot/static/abstract.jpg
dischub_bot/static/abstract2.jpg
dischub_bot/static/icon.jpg
dischub_bot/static/assets/online-transactions.png
dischub_bot/static/assets/secure-transactions.png
dischub_bot/static/assets/user.png
dischub_bot/static/css/style.css
dischub_bot/static/images/favicon.ico
dischub_bot/static/images/favicon.png
dischub_bot/templates/400.html
dischub_bot/templates/401.html
dischub_bot/templates/403.html
dischub_bot/templates/404.html
dischub_bot/templates/500.html
dischub_bot/templates/502.html
dischub_bot/templates/base.html
dischub_bot/templates/guidelines.html
dischub_bot/templates/index.html
dischub_bot/templates/manage_bot.html
dischub_bot/templates/codes/400.html
dischub_bot/templates/codes/401.html
dischub_bot/templates/codes/403.html
dischub_bot/templates/codes/404.html
dischub_bot/templates/codes/500.html
dischub_bot/templates/codes/502.html
dischub_bot/templates/components/alert_bar.html
dischub_bot/templates/components/image_loader.html
dischub_bot/templates/components/logo_spinner.html
dischub_bot/templates/components/messages.html
dischub_bot/templates/header/footer.html
dischub_bot-0.1.9.dist-info/METADATA
dischub_bot-0.1.9.dist-info/WHEEL
dischub_bot-0.1.9.dist-info/entry_points.txt
dischub_bot-0.1.9.dist-info/top_level.txt
dischub_bot-0.1.9.dist-info/RECORD
