Metadata-Version: 2.4
Name: dischub_bot
Version: 0.1.9
Summary: Dischub automated scalping bot for MetaTrader 5
Home-page: https://dischub.co.zw
Author: DiscHub
Author-email: chihoyistanford@gmail.com
Classifier: Programming Language :: Python :: 3
Classifier: Operating System :: Microsoft :: Windows
Classifier: License :: OSI Approved :: MIT License
Requires-Python: >=3.9
Requires-Dist: MetaTrader5
Requires-Dist: requests
Requires-Dist: django>=4.2
Dynamic: author
Dynamic: author-email
Dynamic: classifier
Dynamic: description
Dynamic: description-content-type
Dynamic: home-page
Dynamic: requires-dist
Dynamic: requires-python
Dynamic: summary
